src/__init__.py
src/main.py
src/connectors/__init__.py
src/connectors/base_connector.py
src/connectors/google_drive_connector.py
src/models/__init__.py
src/models/document.py
src/models/search.py
src/plugins/__init__.py
src/plugins/base_plugin.py
src/server/__init__.py
src/server/mcp_server.py
src/server/search_orchestrator.py
document_search_mcp-0.1.0.dist-info/METADATA
document_search_mcp-0.1.0.dist-info/WHEEL
document_search_mcp-0.1.0.dist-info/entry_points.txt
document_search_mcp-0.1.0.dist-info/RECORD
