Metadata-Version: 2.4
Name: document-search-mcp
Version: 0.1.0
Summary: Document Search MCP Server with extensible plugin architecture
Project-URL: Homepage, https://github.com/your-org/document-search-mcp
Project-URL: Documentation, https://github.com/your-org/document-search-mcp/docs
Project-URL: Repository, https://github.com/your-org/document-search-mcp
Project-URL: Issues, https://github.com/your-org/document-search-mcp/issues
Author-email: Document Search MCP <admin@example.com>
License: MIT
Keywords: ai,claude,confluence,document-search,google-drive,mcp
Classifier: Development Status :: 3 - Alpha
Classifier: Intended Audience :: Developers
Classifier: License :: OSI Approved :: MIT License
Classifier: Programming Language :: Python :: 3
Classifier: Programming Language :: Python :: 3.11
Classifier: Programming Language :: Python :: 3.12
Requires-Python: >=3.11
Requires-Dist: aiofiles>=23.0.0
Requires-Dist: aiohttp>=3.8.0
Requires-Dist: atlassian-python-api>=3.40.0
Requires-Dist: click>=8.1.0
Requires-Dist: elasticsearch>=8.10.0
Requires-Dist: faiss-cpu>=1.7.4
Requires-Dist: google-api-python-client>=2.100.0
Requires-Dist: google-auth-httplib2>=0.2.0
Requires-Dist: google-auth-oauthlib>=1.0.0
Requires-Dist: google-auth>=2.20.0
Requires-Dist: httpx>=0.25.0
Requires-Dist: mcp>=1.0.0
Requires-Dist: pydantic>=2.0.0
Requires-Dist: python-dotenv>=1.0.0
Requires-Dist: pyyaml>=6.0
Requires-Dist: rich>=13.0.0
Requires-Dist: sentence-transformers>=2.2.0
Requires-Dist: structlog>=23.0.0
Provides-Extra: dev
Requires-Dist: bandit>=1.7.0; extra == 'dev'
Requires-Dist: black>=23.0.0; extra == 'dev'
Requires-Dist: mypy>=1.5.0; extra == 'dev'
Requires-Dist: pre-commit>=3.0.0; extra == 'dev'
Requires-Dist: pytest-asyncio>=0.21.0; extra == 'dev'
Requires-Dist: pytest-cov>=4.0.0; extra == 'dev'
Requires-Dist: pytest-mock>=3.10.0; extra == 'dev'
Requires-Dist: pytest>=7.0.0; extra == 'dev'
Requires-Dist: ruff>=0.1.0; extra == 'dev'
Requires-Dist: safety>=2.0.0; extra == 'dev'
Requires-Dist: sphinx-autodoc-typehints>=1.24.0; extra == 'dev'
Requires-Dist: sphinx>=7.0.0; extra == 'dev'
Requires-Dist: types-pyyaml>=6.0.0; extra == 'dev'
Requires-Dist: types-requests>=2.31.0; extra == 'dev'
Provides-Extra: search-engines
Requires-Dist: pinecone-client>=2.2.0; extra == 'search-engines'
Requires-Dist: typesense>=0.25.0; extra == 'search-engines'
Requires-Dist: weaviate-client>=3.25.0; extra == 'search-engines'
